setup.py
latest_repo/__init__.py
latest_repo.egg-info/PKG-INFO
latest_repo.egg-info/SOURCES.txt
latest_repo.egg-info/dependency_links.txt
latest_repo.egg-info/not-zip-safe
latest_repo.egg-info/top_level.txt