Metadata-Version: 1.0
Name: latest-repo
Version: 0.1
Summary: Get latest repository of any GitHub user or organisation
Home-page: http://github.com/storborg/funniest
Author: Marta Zaryn
Author-email: martazaryn@gmail.com
License: MIT
Platform: UNKNOWN
